fin_infra/__init__.py
fin_infra/__main__.py
fin_infra/analytics/__init__.py
fin_infra/analytics/add.py
fin_infra/analytics/benchmark.py
fin_infra/analytics/cash_flow.py
fin_infra/analytics/ease.py
fin_infra/analytics/models.py
fin_infra/analytics/portfolio.py
fin_infra/analytics/projections.py
fin_infra/analytics/rebalancing.py
fin_infra/analytics/rebalancing_llm.py
fin_infra/analytics/savings.py
fin_infra/analytics/scenarios.py
fin_infra/analytics/spending.py
fin_infra/banking/__init__.py
fin_infra/banking/history.py
fin_infra/banking/utils.py
fin_infra/brokerage/__init__.py
fin_infra/budgets/__init__.py
fin_infra/budgets/add.py
fin_infra/budgets/alerts.py
fin_infra/budgets/ease.py
fin_infra/budgets/models.py
fin_infra/budgets/scaffold_templates/README.md
fin_infra/budgets/scaffold_templates/__init__.py
fin_infra/budgets/scaffold_templates/models.py.tmpl
fin_infra/budgets/scaffold_templates/repository.py.tmpl
fin_infra/budgets/scaffold_templates/schemas.py.tmpl
fin_infra/budgets/templates.py
fin_infra/budgets/tracker.py
fin_infra/cashflows/__init__.py
fin_infra/cashflows/core.py
fin_infra/categorization/__init__.py
fin_infra/categorization/add.py
fin_infra/categorization/ease.py
fin_infra/categorization/engine.py
fin_infra/categorization/llm_layer.py
fin_infra/categorization/models.py
fin_infra/categorization/rules.py
fin_infra/categorization/taxonomy.py
fin_infra/chat/__init__.py
fin_infra/chat/ease.py
fin_infra/chat/planning.py
fin_infra/cli/__init__.py
fin_infra/cli/cmds/__init__.py
fin_infra/cli/cmds/scaffold_cmds.py
fin_infra/clients/__init__.py
fin_infra/clients/base.py
fin_infra/clients/plaid.py
fin_infra/compliance/__init__.py
fin_infra/credit/__init__.py
fin_infra/credit/add.py
fin_infra/credit/experian/__init__.py
fin_infra/credit/experian/auth.py
fin_infra/credit/experian/client.py
fin_infra/credit/experian/parser.py
fin_infra/credit/experian/provider.py
fin_infra/credit/mock.py
fin_infra/crypto/__init__.py
fin_infra/crypto/insights.py
fin_infra-0.8.0.dist-info/LICENSE
fin_infra-0.8.0.dist-info/METADATA
fin_infra-0.8.0.dist-info/WHEEL
fin_infra-0.8.0.dist-info/entry_points.txt
fin_infra-0.8.0.dist-info/RECORD
