Metadata-Version: 2.3
Name: fin-infra
Version: 0.8.0
Summary: Financial infrastructure toolkit: banking connections, market data, credit, cashflows, and brokerage integrations
License: MIT
Keywords: finance,banking,plaid,brokerage,markets,credit,tax,cashflow,fintech,infra
Author: Ali Khatami
Author-email: aliikhatami94@gmail.com
Requires-Python: >=3.11,<4.0
Classifier: Development Status :: 3 - Alpha
Classifier: Framework :: FastAPI
Classifier: Intended Audience :: Developers
Classifier: License :: OSI Approved :: MIT License
Classifier: Programming Language :: Python :: 3
Classifier: Programming Language :: Python :: 3.11
Classifier: Programming Language :: Python :: 3.12
Classifier: Programming Language :: Python :: 3.13
Classifier: Programming Language :: Python :: 3 :: Only
Classifier: Topic :: Office/Business :: Financial
Classifier: Topic :: Software Development :: Libraries :: Python Modules
Classifier: Typing :: Typed
Provides-Extra: all
Provides-Extra: banking
Provides-Extra: crypto
Provides-Extra: markets
Provides-Extra: plaid
Provides-Extra: yahoo
Requires-Dist: ai-infra (>=0.1.142)
Requires-Dist: authlib (>=1.6.6)
Requires-Dist: cashews[redis] (>=7.0)
Requires-Dist: ccxt (>=4.0.0) ; extra == "markets" or extra == "crypto" or extra == "all"
Requires-Dist: fastapi-users (>=15.0.2,<16.0.0)
Requires-Dist: filelock (>=3.20.3)
Requires-Dist: httpx (>=0.25.0)
Requires-Dist: langchain-core (>=1.2.5,<2.0.0)
Requires-Dist: loguru (>=0.7.0)
Requires-Dist: numpy (>=1.24.0)
Requires-Dist: numpy-financial (>=1.0.0)
Requires-Dist: plaid-python (>=25.0.0) ; extra == "plaid" or extra == "banking" or extra == "all"
Requires-Dist: protobuf (>=6.33.3)
Requires-Dist: pydantic (>=2.0)
Requires-Dist: pydantic-settings (>=2.0)
Requires-Dist: python-dotenv (>=1.0.0)
Requires-Dist: tenacity (>=8.0.0)
Requires-Dist: typing-extensions (>=4.0)
Requires-Dist: urllib3 (>=2.6.3)
Requires-Dist: virtualenv (>=20.36.1)
Requires-Dist: werkzeug (>=3.1.5)
Requires-Dist: yahooquery (>=2.3.0) ; extra == "markets" or extra == "yahoo" or extra == "all"
Project-URL: Documentation, https://nfrax.com/fin-infra
Project-URL: Homepage, https://github.com/nfraxlab/fin-infra
Project-URL: Issues, https://github.com/nfraxlab/fin-infra/issues
Project-URL: Repository, https://github.com/nfraxlab/fin-infra
